MANIFEST.in
README.md
license.txt
setup.py
jars/mysql-connector-java-8.0.29.jar
jars/nmd.jar
jars/postgresql-42.4.0.jar
nhapp.egg-info/PKG-INFO
nhapp.egg-info/SOURCES.txt
nhapp.egg-info/dependency_links.txt
nhapp.egg-info/requires.txt
nhapp.egg-info/top_level.txt
nmdi/ReadMinio.py
nmdi/__init__.py