Metadata-Version: 2.1
Name: nhapp
Version: 0.0.9.6
Summary: inspire your love 
Author: Nguyen Manh Dung 
Author-email: 123456zvn2@gmail.com
Classifier: Programming Language :: Python :: 3
Classifier: License :: OSI Approved :: MIT License
Classifier: Operating System :: OS Independent
Requires-Python: >=3.8
License-File: license.txt
